esmvaltool/__init__.py
esmvaltool/config-references.yml
esmvaltool/cmorizers/data/__init__.py
esmvaltool/cmorizers/data/cmorizer.py
esmvaltool/cmorizers/data/datasets.yml
esmvaltool/cmorizers/data/datasets_schema.yml
esmvaltool/cmorizers/data/utilities.py
esmvaltool/cmorizers/data/cmor_config/AERONET.yml
esmvaltool/cmorizers/data/cmor_config/AGCD.yml
esmvaltool/cmorizers/data/cmor_config/ANUClimate.yml
esmvaltool/cmorizers/data/cmor_config/APHRO-MA.yml
esmvaltool/cmorizers/data/cmor_config/BerkeleyEarth.yml
esmvaltool/cmorizers/data/cmor_config/CAMS.yml
esmvaltool/cmorizers/data/cmor_config/CDS-SATELLITE-ALBEDO.yml
esmvaltool/cmorizers/data/cmor_config/CDS-SATELLITE-LAI-FAPAR.yml
esmvaltool/cmorizers/data/cmor_config/CDS-SATELLITE-SOIL-MOISTURE.ncl
esmvaltool/cmorizers/data/cmor_config/CDS-UERRA.yml
esmvaltool/cmorizers/data/cmor_config/CERES-EBAF.yml
esmvaltool/cmorizers/data/cmor_config/CMAP.yml
esmvaltool/cmorizers/data/cmor_config/CRU.yml
esmvaltool/cmorizers/data/cmor_config/CT2019.yml
esmvaltool/cmorizers/data/cmor_config/CowtanWay.yml
esmvaltool/cmorizers/data/cmor_config/Duveiller2018.yml
esmvaltool/cmorizers/data/cmor_config/E-OBS.yml
esmvaltool/cmorizers/data/cmor_config/ERA-Interim-Land.yml
esmvaltool/cmorizers/data/cmor_config/ERA-Interim.yml
esmvaltool/cmorizers/data/cmor_config/ESACCI-BIOMASS.yml
esmvaltool/cmorizers/data/cmor_config/ESACCI-CLOUD.yml
esmvaltool/cmorizers/data/cmor_config/ESACCI-LANDCOVER.yml
esmvaltool/cmorizers/data/cmor_config/ESACCI-LST.yml
esmvaltool/cmorizers/data/cmor_config/ESACCI-OC.yml
esmvaltool/cmorizers/data/cmor_config/ESACCI-OZONE.yml
esmvaltool/cmorizers/data/cmor_config/ESACCI-SEA-SURFACE-SALINITY.yml
esmvaltool/cmorizers/data/cmor_config/ESACCI-SEAICE.yml
esmvaltool/cmorizers/data/cmor_config/ESACCI-SOILMOISTURE.yml
esmvaltool/cmorizers/data/cmor_config/ESACCI-SST.yml
esmvaltool/cmorizers/data/cmor_config/ESACCI-WATERVAPOUR.yml
esmvaltool/cmorizers/data/cmor_config/ESDC.yml
esmvaltool-2.13.0.dist-info/licenses/LICENSE
esmvaltool-2.13.0.dist-info/METADATA
esmvaltool-2.13.0.dist-info/WHEEL
esmvaltool-2.13.0.dist-info/entry_points.txt
esmvaltool-2.13.0.dist-info/top_level.txt
esmvaltool-2.13.0.dist-info/RECORD
