Metadata-Version: 2.4
Name: ESMValTool
Version: 2.13.0
Summary: A community tool for pre-processing data from Earth system models in CMIP and running analysis scripts
Author-email: ESMValTool Development Team <esmvaltool-dev@listserv.dfn.de>
License: Apache License, Version 2.0
Project-URL: Code, https://github.com/ESMValGroup/ESMValTool
Project-URL: Community, https://github.com/ESMValGroup/Community
Project-URL: Documentation, https://docs.esmvaltool.org
Project-URL: Homepage, https://esmvaltool.org
Project-URL: Issues, https://github.com/ESMValGroup/ESMValTool/issues
Classifier: Development Status :: 5 - Production/Stable
Classifier: Environment :: Console
Classifier: Intended Audience :: Developers
Classifier: Intended Audience :: Science/Research
Classifier: License :: OSI Approved :: Apache Software License
Classifier: Natural Language :: English
Classifier: Operating System :: POSIX :: Linux
Classifier: Programming Language :: Python :: 3
Classifier: Programming Language :: Python :: 3.11
Classifier: Programming Language :: Python :: 3.12
Classifier: Programming Language :: Python :: 3.13
Classifier: Topic :: Scientific/Engineering
Classifier: Topic :: Scientific/Engineering :: Atmospheric Science
Classifier: Topic :: Scientific/Engineering :: GIS
Classifier: Topic :: Scientific/Engineering :: Hydrology
Classifier: Topic :: Scientific/Engineering :: Physics
Requires-Python: >=3.11
License-File: LICENSE
Requires-Dist: aiohttp
Requires-Dist: arviz
Requires-Dist: cartopy
Requires-Dist: cdo
Requires-Dist: cdsapi
Requires-Dist: cf-units
Requires-Dist: cfgrib
Requires-Dist: cftime
Requires-Dist: cmocean
Requires-Dist: dask!=2024.8.0
Requires-Dist: distributed
Requires-Dist: ecmwf-api-client
Requires-Dist: eofs
Requires-Dist: ESMPy
Requires-Dist: esmvalcore
Requires-Dist: esmf-regrid>=0.10.0
Requires-Dist: fiona
Requires-Dist: fire
Requires-Dist: fsspec
Requires-Dist: GDAL
Requires-Dist: ipython<9.0
Requires-Dist: jinja2
Requires-Dist: joblib
Requires-Dist: lime
Requires-Dist: mapgenerator>=1.0.5
Requires-Dist: matplotlib
Requires-Dist: natsort
Requires-Dist: nc-time-axis
Requires-Dist: netCDF4
Requires-Dist: numba
Requires-Dist: numpy!=1.24.3
Requires-Dist: openpyxl
Requires-Dist: packaging
Requires-Dist: pandas
Requires-Dist: progressbar2
Requires-Dist: pyproj>=2.1
Requires-Dist: pys2index
Requires-Dist: python-dateutil
Requires-Dist: pyyaml
Requires-Dist: rasterio>=1.3.10
Requires-Dist: requests
Requires-Dist: ruamel.yaml
Requires-Dist: scikit-image
Requires-Dist: scikit-learn>=1.4.0
Requires-Dist: scipy
Requires-Dist: scitools-iris>=3.11
Requires-Dist: seaborn
Requires-Dist: seawater
Requires-Dist: shapely>=2
Requires-Dist: xarray>=0.12.0
Requires-Dist: xesmf>=0.7.1
Requires-Dist: xgboost>1.6.1
Requires-Dist: xlsxwriter
Requires-Dist: zarr
Provides-Extra: test
Requires-Dist: pre-commit; extra == "test"
Requires-Dist: pytest>6.0.0; extra == "test"
Requires-Dist: pytest-cov>=2.10.1; extra == "test"
Requires-Dist: pytest-env; extra == "test"
Requires-Dist: pytest-html!=2.1.0; extra == "test"
Requires-Dist: pytest-metadata>=1.5.1; extra == "test"
Requires-Dist: pytest-mock; extra == "test"
Requires-Dist: pytest-xdist; extra == "test"
Provides-Extra: doc
Requires-Dist: autodocsumm>=0.2.2; extra == "doc"
Requires-Dist: nbsphinx; extra == "doc"
Requires-Dist: sphinx>=6.1.3; extra == "doc"
Requires-Dist: pydata_sphinx_theme; extra == "doc"
Provides-Extra: develop
Requires-Dist: esmvaltool[doc,test]; extra == "develop"
Requires-Dist: codespell; extra == "develop"
Requires-Dist: docformatter; extra == "develop"
Requires-Dist: imagehash; extra == "develop"
Requires-Dist: pre-commit; extra == "develop"
Requires-Dist: prospector[with_pyroma]>=1.12; extra == "develop"
Requires-Dist: vprof; extra == "develop"
Requires-Dist: yamllint; extra == "develop"
Dynamic: license-file
